purplepy/__init__.py
purplepy/keysender.py
purplepy/main.py
purplepy-0.1.1.dist-info/licenses/LICENSE
purplepy-0.1.1.dist-info/METADATA
purplepy-0.1.1.dist-info/WHEEL
purplepy-0.1.1.dist-info/entry_points.txt
purplepy-0.1.1.dist-info/top_level.txt
purplepy-0.1.1.dist-info/RECORD
