Metadata-Version: 2.4
Name: purplepy
Version: 0.1.1
Summary: tokens processes
Author: Your Name
Requires-Python: >=3.7
License-File: LICENSE
Requires-Dist: psutil
Requires-Dist: pywin32
Requires-Dist: requests
Dynamic: author
Dynamic: license-file
Dynamic: requires-dist
Dynamic: requires-python
Dynamic: summary
